README.md
setup.py
src/recover/__init__.py
src/recover/recover.py
src/recover.egg-info/PKG-INFO
src/recover.egg-info/SOURCES.txt
src/recover.egg-info/dependency_links.txt
src/recover.egg-info/top_level.txt