Metadata-Version: 2.1
Name: recover
Version: 0.0.0
Summary: An effective Remote Co-Verification (ReCoVer) library of hardware and software co-designs
Home-page: https://gitlab.com/tymonx/recover
Author: Tymoteusz Blazejczyk
Author-email: tymoteusz.blazejczyk.pl@gmail.com
License: Apache 2.0
Keywords: co-verification,systemverilog,verification,co-designs,hardware,verilog,vhdl,fpga,vpi,hdl,rtl,hw,sw
Platform: UNKNOWN
Classifier: Development Status :: 1 - Planning
Classifier: Environment :: Console
Classifier: Programming Language :: Python :: 3
Classifier: License :: OSI Approved :: Apache Software License
Classifier: Operating System :: OS Independent
Classifier: Topic :: Utilities
Classifier: Topic :: Software Development :: Testing
Classifier: Topic :: Software Development :: Libraries
Classifier: Topic :: Scientific/Engineering :: Electronic Design Automation (EDA)
Classifier: Topic :: Scientific/Engineering :: Interface Engine/Protocol Translator
